ae/sys_data_sh.py
ae_sys_data_sh-0.3.8.dist-info/LICENSE.md
ae_sys_data_sh-0.3.8.dist-info/METADATA
ae_sys_data_sh-0.3.8.dist-info/WHEEL
ae_sys_data_sh-0.3.8.dist-info/top_level.txt
ae_sys_data_sh-0.3.8.dist-info/zip-safe
ae_sys_data_sh-0.3.8.dist-info/RECORD
